motordecalidad/_init_.py
motordecalidad/constants.py
motordecalidad/field.py
motordecalidad/functions.py
motordecalidad/rules.py
motordecalidad/utilities.py
MotorDeCalidad-2.2.18.dist-info/METADATA
MotorDeCalidad-2.2.18.dist-info/WHEEL
MotorDeCalidad-2.2.18.dist-info/top_level.txt
MotorDeCalidad-2.2.18.dist-info/RECORD
