Metadata-Version: 2.1
Name: MotorDeCalidad
Version: 2.2.18
Summary: Paquete demo de Motor de Calidad
Author: Enzo Ipanaque
Author-email: enzo.ipanaque@ms-peru.com
License: Management Solutions
Requires-Dist: azure-storage-blob
Requires-Dist: typing-extensions ==4.5.0
